svine/__init__.py
svine/exceptions.py
svine/remote.py
svine-0.2.1.dist-info/licenses/LICENSES/CC-BY-4.0.txt
svine-0.2.1.dist-info/licenses/LICENSES/CC0-1.0.txt
svine-0.2.1.dist-info/licenses/LICENSES/MIT.txt
svine-0.2.1.dist-info/WHEEL
svine-0.2.1.dist-info/METADATA
svine-0.2.1.dist-info/RECORD
