Metadata-Version: 2.4
Name: svine
Version: 0.2.1
Summary: A simple Python wrapper for a limited number of svn commands for mining Subversion repositories.
Author: Stephan Druskat
Author-email: Stephan Druskat <stephan.druskat@dlr.de>
License-Expression: MIT AND CC0-1.0 AND CC-BY-4.0
License-File: LICENSES/CC-BY-4.0.txt
License-File: LICENSES/CC0-1.0.txt
License-File: LICENSES/MIT.txt
Classifier: Development Status :: 4 - Beta
Classifier: Intended Audience :: Developers
Classifier: Intended Audience :: Science/Research
Classifier: License :: OSI Approved :: MIT License
Requires-Dist: python-dateutil>=2.9.0.post0,<3
Maintainer: Stephan Druskat
Maintainer-email: Stephan Druskat <stephan.druskat@dlr.de>
Requires-Python: >=3.11
